{
    "posts": [
        {
            "id": 1,
            "title": "Welcome to first Blog",
            "body": "Lorem ipsum dolor sit amet consectetur, adipisicing elit. Quod veniam velit sunt quaerat magnam distinctio temporibus maiores vero ipsum. Explicabo incidunt itaqueexcepturi esse quam autem, eaque odit nesciunt, officia culpa beatae ut vero vitaequaerat odio cumque tenetur maxime iure ducimus quos. Sunt saepe quisquam nostrumofficiis corrupti? Sed ex molestiae quo nam, qui dolorem sapiente maxime? Perferendissequi commodi iure optio modi mollitia sed debitis. Accusamus ratione porro est exvoluptatum consequatur laboriosam, cumque sapiente facilis tenetur in alias aliquamrecusandae nam, harum sequi ipsa natus? Ratione soluta, repellat odio temporemolestias rerum, at nisi atque possimus nemo assumenda quas! Labore impedit quaeratquasi illum nulla quas totam incidunt ipsam omnis, optio aliquid quidem officia eiusiste, sit natus dolorem soluta dolores harum? Doloribus amet neque fuga quod, sed remaccusantium quos voluptatem ad tenetur error ducimus id quia nesciunt corporis minus,beatae nemo, optio natus aperiam alias saepe reprehenderit? Atque aperiam quidemratione ut sint in, et tempore dolorem quasi totam soluta nobis iste a laboriosamamet? Nobis sapiente quo ullam animi ad architecto tempore reiciendis sequi facere,modi incidunt explicabo id dolor assumenda commodi voluptatem ipsum neque aliquamculpa eos earum itaque quibusdam eligendi. Distinctio animi atque dolor, accusamus quiexcepturi repudiandae sequi voluptatem voluptas nemo natus eum cumque enim iurefacilis, consectetur quaerat ipsum eos cum assumenda quae. Labore in voluptatesratione ducimus delectus itaque deleniti maiores mollitia harum sint, inventoredolorem a quisquam explicabo id laboriosam sunt distinctio fuga, quis aut commodisapiente minus ullam! Harum nisi quia, nemo recusandae tempora optio quod nostrumvoluptates eum neque tenetur obcaecati quos labore minima nesciunt consequuntur,voluptate quis eos soluta quae incidunt non est? Doloribus nihil praesentiumrepudiandae rem ipsa esse illo, neque tenetur aliquid blanditiis saepe cumque, ex quiadolore mollitia cupiditate quisquam veritatis quod? Explicabo aperiam architecto porronecessitatibus rerum non, dolor illo assumenda repellat provident possimus eos harumeveniet accusantium est iste",
            "tags": [
                "webdev",
                "codign",
                "news"
            ]
        },
        {
            "id": 2,
            "title": "Welcome to second Blog",
            "body": "adipisicing elit. Quod veniam velit sunt quaerat magnam distinctio temporibus maiores vero ipsum. Explicabo incidunt itaqueexcepturi esse quam autem, eaque odit nesciunt, officia culpa beatae ut vero vitaequaerat odio cumque tenetur maxime iure ducimus quos. Sunt saepe quisquam nostrumofficiis corrupti? Sed ex molestiae quo nam, qui dolorem sapiente maxime? Perferendissequi commodi iure optio modi mollitia sed debitis. Accusamus ratione porro est exvoluptatum consequatur laboriosam, cumque sapiente facilis tenetur in alias aliquamrecusandae nam, harum sequi ipsa natus? Ratione soluta, repellat odio temporemolestias rerum, at nisi atque possimus nemo assumenda quas! Labore impedit quaeratquasi illum nulla quas totam incidunt ipsam omnis, optio aliquid quidem officia eiusiste, sit natus dolorem soluta dolores harum? Doloribus amet neque fuga quod, sed remaccusantium quos voluptatem ad tenetur error ducimus id quia nesciunt corporis minus,beatae nemo, optio natus aperiam alias saepe reprehenderit? Atque aperiam quidemratione ut sint in, et tempore dolorem quasi totam soluta nobis iste a laboriosamamet? Nobis sapiente quo ullam animi ad architecto tempore reiciendis sequi facere,modi incidunt explicabo id dolor assumenda commodi voluptatem ipsum neque aliquamculpa eos earum itaque quibusdam eligendi. Distinctio animi atque dolor, accusamus quiexcepturi repudiandae sequi voluptatem voluptas nemo natus eum cumque enim iurefacilis, consectetur quaerat ipsum eos cum assumenda quae. Labore in voluptatesratione ducimus delectus itaque deleniti maiores mollitia harum sint, inventoredolorem a quisquam explicabo id laboriosam sunt distinctio fuga, quis aut commodisapiente minus ullam! Harum nisi quia, nemo recusandae tempora optio quod nostrumvoluptates eum neque tenetur obcaecati quos labore minima nesciunt consequuntur,voluptate quis eos soluta quae incidunt non est? Doloribus nihil praesentiumrepudiandae rem ipsa esse illo, neque tenetur aliquid blanditiis saepe cumque, ex quiadolore mollitia cupiditate quisquam veritatis quod? Explicabo aperiam architecto porronecessitatibus rerum non, dolor illo assumenda repellat provident possimus eos harumeveniet accusantium est iste",
            "tags": [
                "css",
                "scss",
                "lass"
            ]
        },
        {
            "id": 2,
            "title": "Welcome to second Blog",
            "body": "adipisicing elit. Quod veniam velit sunt quaerat magnam distinctio temporibus maiores vero ipsum. Explicabo incidunt itaqueexcepturi esse quam autem, eaque odit nesciunt, officia culpa beatae ut vero vitaequaerat odio cumque tenetur maxime iure ducimus quos. Sunt saepe quisquam nostrumofficiis corrupti? Sed ex molestiae quo nam, qui dolorem sapiente maxime? Perferendissequi commodi iure optio modi mollitia sed debitis. Accusamus ratione porro est exvoluptatum consequatur laboriosam, cumque sapiente facilis tenetur in alias aliquamrecusandae nam, harum sequi ipsa natus? Ratione soluta, repellat odio temporemolestias rerum, at nisi atque possimus nemo assumenda quas! Labore impedit quaeratquasi illum nulla quas totam incidunt ipsam omnis, optio aliquid quidem officia eiusiste, sit natus dolorem soluta dolores harum? Doloribus amet neque fuga quod, sed remaccusantium quos voluptatem ad tenetur error ducimus id quia nesciunt corporis minus,beatae nemo, optio natus aperiam alias saepe reprehenderit? Atque aperiam quidemratione ut sint in, et tempore dolorem quasi totam soluta nobis iste a laboriosamamet? Nobis sapiente quo ullam animi ad architecto tempore reiciendis sequi facere,modi incidunt explicabo id dolor assumenda commodi voluptatem ipsum neque aliquamculpa eos earum itaque quibusdam eligendi. Distinctio animi atque dolor, accusamus quiexcepturi repudiandae sequi voluptatem voluptas nemo natus eum cumque enim iurefacilis, consectetur quaerat ipsum eos cum assumenda quae. Labore in voluptatesratione ducimus delectus itaque deleniti maiores mollitia harum sint, inventoredolorem a quisquam explicabo id laboriosam sunt distinctio fuga, quis aut commodisapiente minus ullam! Harum nisi quia, nemo recusandae tempora optio quod nostrumvoluptates eum neque tenetur obcaecati quos labore minima nesciunt consequuntur,voluptate quis eos soluta quae incidunt non est? Doloribus nihil praesentiumrepudiandae rem ipsa esse illo, neque tenetur aliquid blanditiis saepe cumque, ex quiadolore mollitia cupiditate quisquam veritatis quod? Explicabo aperiam architecto porronecessitatibus rerum non, dolor illo assumenda repellat provident possimus eos harumeveniet accusantium est iste",
            "tags": [
                "css",
                "scss",
                "lass"
            ]
        }
    ]
}